odoo10_addon_web_widget_image_webcam-10.0.1.0.0-py2.7-nspkg.pth
odoo/addons/web_widget_image_webcam/README.rst
odoo/addons/web_widget_image_webcam/__init__.py
odoo/addons/web_widget_image_webcam/__manifest__.py
odoo/addons/web_widget_image_webcam/static/description/icon.png
odoo/addons/web_widget_image_webcam/static/src/css/web_widget_image_webcam.css
odoo/addons/web_widget_image_webcam/static/src/img/webcam_placeholder.png
odoo/addons/web_widget_image_webcam/static/src/js/webcam.js
odoo/addons/web_widget_image_webcam/static/src/js/webcam.swf
odoo/addons/web_widget_image_webcam/static/src/js/webcam_widget.js
odoo/addons/web_widget_image_webcam/static/src/xml/web_widget_image_webcam.xml
odoo/addons/web_widget_image_webcam/views/assets.xml
odoo10_addon_web_widget_image_webcam-10.0.1.0.0.dist-info/DESCRIPTION.rst
odoo10_addon_web_widget_image_webcam-10.0.1.0.0.dist-info/METADATA
odoo10_addon_web_widget_image_webcam-10.0.1.0.0.dist-info/RECORD
odoo10_addon_web_widget_image_webcam-10.0.1.0.0.dist-info/WHEEL
odoo10_addon_web_widget_image_webcam-10.0.1.0.0.dist-info/metadata.json
odoo10_addon_web_widget_image_webcam-10.0.1.0.0.dist-info/namespace_packages.txt
odoo10_addon_web_widget_image_webcam-10.0.1.0.0.dist-info/top_level.txt
