Metadata-Version: 2.0
Name: odoo10-addon-web-widget-image-webcam
Version: 10.0.1.0.0
Summary: Allows to take image with WebCam
Home-page: https://www.techreceptives.com
Author: Tech Receptives, Odoo Community Association (OCA), Kaushal Prajapati
Author-email: support@odoo-community.org
License: LGPL-3
Platform: UNKNOWN
Classifier: Programming Language :: Python :: 2.7
Classifier: Framework :: Odoo
Classifier: License :: OSI Approved :: GNU Lesser General Public License v3 (LGPLv3)
Requires-Dist: odoo (<10.1dev,>=10.0)
